secret_mit/__init__.py
secret_mit-0.0.1.dist-info/METADATA
secret_mit-0.0.1.dist-info/WHEEL
secret_mit-0.0.1.dist-info/licenses/LICENSE
secret_mit-0.0.1.dist-info/RECORD
