Metadata-Version: 2.3
Name: secret-mit
Version: 0.0.1
Summary: A small package that prints a message when imported
Project-URL: Homepage, https://github.com/yourusername/secret-mit
Project-URL: Bug Tracker, https://github.com/yourusername/secret-mit/issues
Author-email: Your Name <your.email@example.com>
License-File: LICENSE
Classifier: License :: OSI Approved :: MIT License
Classifier: Operating System :: OS Independent
Classifier: Programming Language :: Python :: 3
Requires-Python: >=3.7
